{
  "childName": "AFDO",
  "contacts": [
    "gbiv@chromium.org"
  ],
  "gerrit": {
    "url": "https://chromium-review.googlesource.com",
    "project": "chromium/src",
    "config": "chromium"
  },
  "isInternal": false,
  "parentName": "Chromium",
  "parentWaterfall": "https://build.chromium.org",
  "rollerName": "afdo-chromium-autoroll",
  "serviceAccount": "chromium-autoroll@skia-public.google.com.iam.gserviceaccount.com",
  "sheriff": [
    "gbiv@chromium.org"
  ],
  "afdoRepoManager": {
    "childBranch": "master",
    "childPath": "chrome/android/profiles/newest.txt",
    "parentBranch": "master",
    "parentRepo": "https://chromium.googlesource.com/chromium/src.git"
  },
  "kubernetes": {
    "cpu": "1",
    "memory": "2Gi",
    "disk": "2Gi",
    "readinessInitialDelaySeconds": "30",
    "readinessPeriodSeconds": "30",
    "readinessFailureThreshold": "10"
  },
  "maxRollFrequency": "0m"
}
