{
  "builder_name_schema": {
    "Test": [
      "os",
      "model",
      "gpu",
      "arch",
      "configuration"
    ],
    "Housekeeper": [
      "frequency"
    ],
    "Build": [
      "os",
      "compiler",
      "target_arch",
      "configuration"
    ],
    "Perf": [
      "os",
      "model",
      "gpu",
      "arch",
      "configuration"
    ],
    "Canary": [
      "project",
      "os",
      "compiler",
      "target_arch",
      "configuration"
    ]
  },
  "builder_name_sep": "-",
  "trybot_name_suffix": "Trybot"
}