{
  "Mojo Linux Perf": {
    "alias": "linux-perf-fyi"
  },
  "Win 10 Perf": {
    "alias": "win-10-perf"
  },
  "chromium-rel-win10": {
    "alias": "win-10-perf"
  },
  "linux-release": {
    "alias": "linux-perf"
  },
  "android-go-perf-pgo": {
    "browser": "android-chrome",
    "bucket": "luci.chrome.try",
    "builder": "Android Compile Perf PGO",
    "dimensions": [
      {
        "key": "pool",
        "value": "chrome.tests.pinpoint"
      },
      {
        "key": "device_type",
        "value": "gobo"
      },
      {
        "key": "device_os",
        "value": "OMB1.180119.001"
      }
    ],
    "repository": "chromium",
    "swarming_server": "https://chrome-swarming.appspot.com"
  },
  "android-go-wembley-perf": {
    "browser": "android-trichrome-bundle",
    "bucket": "luci.chrome.try",
    "builder": "Android Compile Perf",
    "dimensions": [
      {
        "key": "pool",
        "value": "chrome.tests.pinpoint"
      },
      {
        "key": "device_type",
        "value": "wembley_2GB"
      }
    ],
    "repository": "chromium",
    "swarming_server": "https://chrome-swarming.appspot.com"
  },
  "android-go-wembley_webview-perf": {
    "browser": "android-webview-google",
    "bucket": "luci.chrome.try",
    "builder": "Android Compile Perf",
    "dimensions": [
      {
        "key": "pool",
        "value": "chrome.tests.pinpoint"
      },
      {
        "key": "device_type",
        "value": "wembley_2GB"
      }
    ],
    "repository": "chromium",
    "swarming_server": "https://chrome-swarming.appspot.com"
  },
  "android-new-pixel-perf": {
    "browser": "android-trichrome-chrome-google-64-32-bundle",
    "bucket": "luci.chrome.try",
    "builder": "Android arm64 Compile Perf",
    "dimensions": [
      {
        "key": "pool",
        "value": "chrome.tests.pinpoint"
      },
      {
        "key": "device_type",
        "value": "panther"
      }
    ],
    "repository": "chromium",
    "swarming_server": "https://chrome-swarming.appspot.com"
  },
  "android-new-pixel-perf-pgo": {
    "browser": "android-trichrome-chrome-google-64-32-bundle",
    "bucket": "luci.chrome.try",
    "builder": "Android arm64 Compile Perf",
    "dimensions": [
      {
        "key": "pool",
        "value": "chrome.tests.pinpoint"
      },
      {
        "key": "device_type",
        "value": "panther"
      }
    ],
    "repository": "chromium",
    "swarming_server": "https://chrome-swarming.appspot.com"
  },
  "android-new-pixel-pro-perf": {
    "browser": "android-trichrome-chrome-google-64-32-bundle",
    "bucket": "luci.chrome.try",
    "builder": "Android arm64 Compile Perf",
    "dimensions": [
      {
        "key": "pool",
        "value": "chrome.tests.pinpoint"
      },
      {
        "key": "device_type",
        "value": "cheetah"
      }
    ],
    "repository": "chromium",
    "swarming_server": "https://chrome-swarming.appspot.com"
  },
  "android-new-pixel-pro-perf-pgo": {
    "browser": "android-trichrome-chrome-google-64-32-bundle",
    "bucket": "luci.chrome.try",
    "builder": "Android arm64 Compile Perf",
    "dimensions": [
      {
        "key": "pool",
        "value": "chrome.tests.pinpoint"
      },
      {
        "key": "device_type",
        "value": "cheetah"
      }
    ],
    "repository": "chromium",
    "swarming_server": "https://chrome-swarming.appspot.com"
  },
  "android-pixel2-perf-fyi": {
    "browser": "android-chrome-64-bundle",
    "bucket": "luci.chrome.try",
    "builder": "Android arm64 Compile Perf",
    "dimensions": [
      {
        "key": "pool",
        "value": "chrome.tests.pinpoint"
      },
      {
        "key": "device_type",
        "value": "walleye"
      },
      {
        "key": "device_os",
        "value": "OPM1.171019.021"
      }
    ],
    "extra_test_args": "--experimental-tbmv3-metrics",
    "repository": "chromium",
    "swarming_server": "https://chrome-swarming.appspot.com"
  },
  "android-pixel2-perf-pgo": {
    "browser": "android-chrome-64-bundle",
    "bucket": "luci.chrome.try",
    "builder": "Android arm64 Compile Perf PGO",
    "dimensions": [
      {
        "key": "pool",
        "value": "chrome.tests.pinpoint"
      },
      {
        "key": "device_type",
        "value": "walleye"
      },
      {
        "key": "device_os",
        "value": "OPM1.171019.021"
      }
    ],
    "repository": "chromium",
    "swarming_server": "https://chrome-swarming.appspot.com"
  },
  "android-pixel2_webview-perf-pgo": {
    "browser": "android-webview-google",
    "bucket": "luci.chrome.try",
    "builder": "Android arm64 Compile Perf PGO",
    "dimensions": [
      {
        "key": "pool",
        "value": "chrome.tests.pinpoint"
      },
      {
        "key": "device_type",
        "value": "walleye"
      },
      {
        "key": "device_os",
        "value": "OPM1.171019.021"
      }
    ],
    "repository": "chromium",
    "swarming_server": "https://chrome-swarming.appspot.com"
  },
  "android-samsung-foldable-perf": {
    "browser": "android-trichrome-bundle",
    "bucket": "luci.chrome.try",
    "builder": "Android arm64 Compile Perf",
    "dimensions": [
      {
        "key": "pool",
        "value": "chrome.tests.pinpoint"
      },
      {
        "key": "device_type",
        "value": "lahaina"
      }
    ],
    "extra_test_args": "--compatibility-mode=dont-require-rooted-device",
    "repository": "chromium",
    "swarming_server": "https://chrome-swarming.appspot.com"
  },
  "mac-10_12_laptop_low_end-perf-pgo": {
    "browser": "release",
    "bucket": "luci.chrome.try",
    "builder": "Mac Builder Perf PGO",
    "dimensions": [
      {
        "key": "pool",
        "value": "chrome.tests.pinpoint"
      },
      {
        "key": "mac_model",
        "value": "MacBookAir7,2"
      },
      {
        "key": "os",
        "value": "Mac-12.6.1"
      },
      {
        "key": "gpu",
        "value": "8086:1626"
      },
      {
        "key": "synthetic_product_name",
        "value": "MacBookAir7,2_x86-64-i5-5350U_Intel Broadwell HD Graphics 6000_8192_APPLE SSD SM0128G"
      }
    ],
    "repository": "chromium",
    "swarming_server": "https://chrome-swarming.appspot.com"
  },
  "mac-10_13_laptop_high_end-perf-pgo": {
    "browser": "release",
    "bucket": "luci.chrome.try",
    "builder": "Mac Builder Perf PGO",
    "dimensions": [
      {
        "key": "pool",
        "value": "chrome.tests.pinpoint"
      },
      {
        "key": "mac_model",
        "value": "MacBookPro11,5"
      },
      {
        "key": "os",
        "value": "Mac-12.6.1"
      },
      {
        "key": "gpu",
        "value": "8086:0d26-4.0.20-3.2.8"
      },
      {
        "key": "synthetic_product_name",
        "value": "MacBookPro11,5_x86-64-i7-4870HQ_AMD Radeon R8 M370X 4.0.20 [3.2.8]_Intel Haswell Iris Pro Graphics 5200 4.0.20 [3.2.8]_16384_APPLE SSD SM0512G"
      }
    ],
    "repository": "chromium",
    "swarming_server": "https://chrome-swarming.appspot.com"
  },
  "mac-laptop_high_end-perf-pgo": {
    "browser": "release",
    "bucket": "luci.chrome.try",
    "builder": "Mac Builder Perf PGO",
    "dimensions": [
      {
        "key": "pool",
        "value": "chrome.tests.pinpoint"
      },
      {
        "key": "mac_model",
        "value": "MacBookPro11,5"
      },
      {
        "key": "os",
        "value": "Mac-12.6.1"
      },
      {
        "key": "gpu",
        "value": "8086:0d26-4.0.20-3.2.8"
      },
      {
        "key": "synthetic_product_name",
        "value": "MacBookPro11,5_x86-64-i7-4870HQ_AMD Radeon R8 M370X 4.0.20 [3.2.8]_Intel Haswell Iris Pro Graphics 5200 4.0.20 [3.2.8]_16384_APPLE SSD SM0512G"
      }
    ],
    "repository": "chromium",
    "swarming_server": "https://chrome-swarming.appspot.com"
  },
  "webrtc-android-tests-pixel2-oreo": {
    "browser": "android-chrome-64-bundle",
    "bucket": "luci.webrtc.perf",
    "builder": "Android64 Builder arm64",
    "dimensions": [
      {
        "key": "pool",
        "value": "chrome.tests.pinpoint"
      },
      {
        "key": "device_type",
        "value": "walleye"
      },
      {
        "key": "device_os",
        "value": "OPM1.171019.021"
      }
    ],
    "repository": "webrtc",
    "swarming_server": "https://chrome-swarming.appspot.com"
  },
  "webrtc-mac-arm64-large-tests": {
    "browser": "release",
    "bucket": "luci.webrtc.perf",
    "builder": "MacArm64 Builder",
    "dimensions": [
      {
        "key": "pool",
        "value": "chrome.tests.pinpoint"
      },
      {
        "key": "mac_model",
        "value": "Macmini9,1"
      },
      {
        "key": "os",
        "value": "Mac"
      },
      {
        "key": "cpu",
        "value": "arm"
      }
    ],
    "repository": "webrtc",
    "swarming_server": "https://chrome-swarming.appspot.com"
  },
  "webrtc-mac-large-tests": {
    "browser": "release",
    "bucket": "luci.webrtc.perf",
    "builder": "Mac64 Builder",
    "dimensions": [
      {
        "key": "pool",
        "value": "chrome.tests.pinpoint"
      },
      {
        "key": "mac_model",
        "value": "MacBookPro11,5"
      },
      {
        "key": "os",
        "value": "Mac-12.6.1"
      },
      {
        "key": "gpu",
        "value": "8086:0d26-4.0.20-3.2.8"
      },
      {
        "key": "synthetic_product_name",
        "value": "MacBookPro11,5_x86-64-i7-4870HQ_AMD Radeon R8 M370X 4.0.20 [3.2.8]_Intel Haswell Iris Pro Graphics 5200 4.0.20 [3.2.8]_16384_APPLE SSD SM0512G"
      }
    ],
    "repository": "webrtc",
    "swarming_server": "https://chrome-swarming.appspot.com"
  },
  "webrtc-win-large-tests": {
    "browser": "release",
    "bucket": "luci.webrtc.perf",
    "builder": "Win32 Builder (Clang)",
    "dimensions": [
      {
        "key": "pool",
        "value": "chrome.tests.pinpoint"
      },
      {
        "key": "synthetic_product_name",
        "value": "OptiPlex 7050 (Dell Inc.)"
      },
      {
        "key": "os",
        "value": "Windows-10"
      }
    ],
    "repository": "webrtc",
    "swarming_server": "https://chrome-swarming.appspot.com"
  },
  "win-10_amd_laptop-perf-pgo": {
    "browser": "release_x64",
    "bucket": "luci.chrome.try",
    "builder": "Win x64 Builder Perf PGO",
    "dimensions": [
      {
        "key": "pool",
        "value": "chrome.tests.pinpoint"
      },
      {
        "key": "os",
        "value": "Windows-10-19043.1052"
      },
      {
        "key": "gpu",
        "value": "1002:1638-30.0.13033.1000"
      },
      {
        "key": "synthetic_product_name",
        "value": "OMEN by HP Laptop 16-c0xxx [ ] (HP)"
      }
    ],
    "repository": "chromium",
    "swarming_server": "https://chrome-swarming.appspot.com"
  },
  "win-10_laptop_low_end-perf-pgo": {
    "browser": "release_x64",
    "bucket": "luci.chrome.try",
    "builder": "Win x64 Builder Perf PGO",
    "dimensions": [
      {
        "key": "pool",
        "value": "chrome.tests.pinpoint"
      },
      {
        "key": "synthetic_product_name",
        "value": "HP Laptop 15-bs1xx [Type1ProductConfigId] (HP)"
      },
      {
        "key": "gpu",
        "value": "8086:1616-20.19.15.5070"
      },
      {
        "key": "os",
        "value": "Windows-10-18363.476"
      }
    ],
    "repository": "chromium",
    "swarming_server": "https://chrome-swarming.appspot.com"
  }
}